snowhut
